odd_even_checker/__init__.py
odd_even_checker/checker.py
odd_even_checker_viswas-0.0.1.dist-info/METADATA
odd_even_checker_viswas-0.0.1.dist-info/WHEEL
odd_even_checker_viswas-0.0.1.dist-info/top_level.txt
odd_even_checker_viswas-0.0.1.dist-info/RECORD
